colorona/__init__.py
colorona-0.2.6.dist-info/METADATA
colorona-0.2.6.dist-info/WHEEL
colorona-0.2.6.dist-info/top_level.txt
colorona-0.2.6.dist-info/RECORD
