Metadata-Version: 2.4
Name: colorona
Version: 0.2.6
Summary: A way to COMPLEATLY transform the way you look and feel about your terminal
Author-email: Your Name <you@example.com>
License: MIT
Requires-Python: >=3.6
